{
    "cuda_gpu" : 1,
    "model_name" : "MLP_LIF_burst_positive_only",
    "num_classes" : 2,
    "num_encoders" : 187,
    "early_stop" : 25,
    "early_stop_enable" : false,
    "init_lr" : 0.001,
    "batch_size" : 256,
    "num_epochs" : 250,
    "train_path" : "/home/hschoi/data/MIT-BIH/mitbih_train.csv",
    "test_path" : "/home/hschoi/data/MIT-BIH/mitbih_test.csv", 
    "class_weight" : [1.0, 4.0], 
    "hidden_size" : 1000,
    "hidden_size_2" : 1000,
    "encoder_min" : 0.2,
    "encoder_max" : 2.0,
    "scheduler_tmax" : 5,
    "scheduler_eta_min" : 0.00001,
    "encoder_requires_grad" : true,
    "timestep" : 128,
    "burst_beta" : 2.0,
    "burst_init_th" : 0.125,
    "random_seed" : 999,
    "checkpoint_save" : true,
    "checkpoint_path" : "/home/hschoi/data/leehyunwon/ECG-SNN/",
    "threshold_value" : 1.0,
    "reset_value_residual" : false,
    "leak_decay" : 2.0,
    "need_bias" : false,
    "negative_penalty_alpha" : 1,
    "saved_model_path" : "/home/hschoi/data/leehyunwon/ECG-SNN/SNN_MLP_ver5_burst_LIF_positive_only_binary_encoders187_hidden1000_encoderGradTrue_early25_lr0.001_threshold1.0_2024_11_05_19_14_43_lastEpoch.pt"
}